cranc/__init__.py
cranc/cranc.py
cranc/utils.py
cranc/commands/__init__.py
cranc/commands/create.py
cranc/commands/get.py
cranc/commands/merge.py
cranc-1.0.1.dist-info/LICENSE
cranc-1.0.1.dist-info/METADATA
cranc-1.0.1.dist-info/WHEEL
cranc-1.0.1.dist-info/dependency_links.txt
cranc-1.0.1.dist-info/entry_points.txt
cranc-1.0.1.dist-info/pbr.json
cranc-1.0.1.dist-info/top_level.txt
cranc-1.0.1.dist-info/RECORD
