Metadata-Version: 2.1
Name: cranc
Version: 1.0.1
Summary: command line interface tool for Pagure pull requests
Home-page: https://pagure.io/cranc
Author: Lenka Segura
Author-email: lenka@sepu.cz
License: UNKNOWN
Platform: UNKNOWN
Requires-Dist: black
Requires-Dist: click
Requires-Dist: git-url-parse
Requires-Dist: libpagure
Requires-Dist: pbr
Requires-Dist: pygit2
Requires-Dist: pytest
Requires-Dist: requests
